Metadata-Version: 2.1
Name: zwsp-char-function
Version: 1.0
Summary: a library that returns a sequence of zero with characters
Home-page: UNKNOWN
Author: Churning Lava
Author-email: snoopydankl@gmail.com
License: MIT
Keywords: zero width character
Platform: UNKNOWN
Classifier: Development Status :: 5 - Production/Stable
Classifier: Intended Audience :: Education
Classifier: Operating System :: Microsoft :: Windows :: Windows 10
Classifier: License :: OSI Approved :: MIT License
Classifier: Programming Language :: Python :: 3
License-File: LICENSE.txt
